byted_overpass_seed_plugin_douyin_video_pack/__init__.py
byted_overpass_seed_plugin_douyin_video_pack-0.0.1.dist-info/METADATA
byted_overpass_seed_plugin_douyin_video_pack-0.0.1.dist-info/WHEEL
byted_overpass_seed_plugin_douyin_video_pack-0.0.1.dist-info/top_level.txt
byted_overpass_seed_plugin_douyin_video_pack-0.0.1.dist-info/RECORD
