Metadata-Version: 2.1
Name: byted-overpass-seed-plugin-douyin-video-pack
Version: 0.0.1
Summary: A simple package named byted_overpass_seed_plugin_douyin_video_pack
Home-page: https://github.com/artifact/byted_overpass_seed_plugin_douyin_video_pack.git
Author: artifact
Author-email: artifact@example.com
License: UNKNOWN
Platform: UNKNOWN
Classifier: Programming Language :: Python :: 3
Classifier: License :: OSI Approved :: MIT License
Classifier: Operating System :: OS Independent
